{
    "nodes": [
        {
            "id": 0,
            "x": 839,
            "y": 274,
            "name": "1층 복도 (보건실/계단)"
        },
        {
            "id": 1,
            "x": 866,
            "y": 274,
            "name": "1층 복도 (보건실)"
        },
        {
            "id": 2,
            "x": 902,
            "y": 274,
            "name": "1층 복도 (보건실)"
        },
        {
            "id": 3,
            "x": 948,
            "y": 274,
            "name": "1층 복도 (학부모실)"
        },
        {
            "id": 4,
            "x": 997,
            "y": 275,
            "name": "1층 복도 (교장실/화장실)"
        },
        {
            "id": 5,
            "x": 1038,
            "y": 274,
            "name": "1층 복도 (행정실/계단)"
        },
        {
            "id": 6,
            "x": 1113,
            "y": 286,
            "name": "1층 외부 정중앙"
        },
        {
            "id": 7,
            "x": 1187,
            "y": 274,
            "name": "1층 복도 (교직원 식당)"
        },
        {
            "id": 8,
            "x": 1230,
            "y": 274,
            "name": "1층 복도 (급식실 화장실)"
        },
        {
            "id": 9,
            "x": 1078,
            "y": 323,
            "name": "1층 복도 (시청각실)"
        },
        {
            "id": 10,
            "x": 1077,
            "y": 358,
            "name": "1층 복도 (시청각실/화장실)"
        },
        {
            "id": 11,
            "x": 839,
            "y": 295,
            "name": "1층 계단 보건실 맞은편"
        },
        {
            "id": 12,
            "x": 839,
            "y": 256,
            "name": "1층 계단 (밖으로 나가는 쪽)"
        },
        {
            "id": 13,
            "x": 869,
            "y": 250,
            "name": "보건실 침대 (여)"
        },
        {
            "id": 14,
            "x": 868,
            "y": 263,
            "name": "보건실 침대 (남)"
        },
        {
            "id": 15,
            "x": 906,
            "y": 256,
            "name": "보건실"
        },
        {
            "id": 16,
            "x": 946,
            "y": 255,
            "name": "학교운영위원회실 (학부모상주실)"
        },
        {
            "id": 17,
            "x": 995,
            "y": 255,
            "name": "교장실"
        },
        {
            "id": 18,
            "x": 1036,
            "y": 256,
            "name": "행정실"
        },
        {
            "id": 19,
            "x": 1040,
            "y": 290,
            "name": "1층 계단 (행정실)"
        },
        {
            "id": 20,
            "x": 1009,
            "y": 298,
            "name": "1층 화장실 (보건실/남)"
        },
        {
            "id": 21,
            "x": 983,
            "y": 299,
            "name": "1층 화장실 (보건실/여)"
        },
        {
            "id": 22,
            "x": 960,
            "y": 298,
            "name": "남직원 휴게실/샤워실"
        },
        {
            "id": 23,
            "x": 936,
            "y": 299,
            "name": "미화원 휴게실/샤워실"
        },
        {
            "id": 24,
            "x": 902,
            "y": 299,
            "name": "당직실"
        },
        {
            "id": 25,
            "x": 867,
            "y": 299,
            "name": "보일러실"
        },
        {
            "id": 26,
            "x": 907,
            "y": 334,
            "name": "당직실 화장실"
        },
        {
            "id": 27,
            "x": 1207,
            "y": 256,
            "name": "교직원 식당"
        },
        {
            "id": 28,
            "x": 1176,
            "y": 290,
            "name": "1층 계단 (교직원 식당)"
        },
        {
            "id": 29,
            "x": 1197,
            "y": 290,
            "name": "승강기"
        },
        {
            "id": 30,
            "x": 1228,
            "y": 284,
            "name": "장애인 화장실 (급식실)"
        },
        {
            "id": 31,
            "x": 1296,
            "y": 297,
            "name": "주방"
        },
        {
            "id": 32,
            "x": 1333,
            "y": 260,
            "name": "학생 식당"
        },
        {
            "id": 33,
            "x": 1347,
            "y": 295,
            "name": "식품 창고"
        },
        {
            "id": 34,
            "x": 1367,
            "y": 295,
            "name": "휴게실 (급식실)"
        },
        {
            "id": 35,
            "x": 1357,
            "y": 319,
            "name": "급식화장실"
        },
        {
            "id": 36,
            "x": 1401,
            "y": 286,
            "name": "샤워실"
        },
        {
            "id": 37,
            "x": 1399,
            "y": 303,
            "name": "보일러실"
        },
        {
            "id": 38,
            "x": 1431,
            "y": 268,
            "name": "1층 계단 (급식실)"
        },
        {
            "id": 39,
            "x": 1431,
            "y": 249,
            "name": "1층 창고 (급식실)"
        },
        {
            "id": 40,
            "x": 1059,
            "y": 338,
            "name": "1층 화장실 (시청각실/남)"
        },
        {
            "id": 41,
            "x": 1060,
            "y": 359,
            "name": "1층 화장실 (시청각실/여)"
        },
        {
            "id": 42,
            "x": 1061,
            "y": 376,
            "name": "1층 계단 (시청각실)"
        },
        {
            "id": 43,
            "x": 1071,
            "y": 390,
            "name": "1층 준비실 (시청각실)"
        },
        {
            "id": 44,
            "x": 1115,
            "y": 403,
            "name": "무대 (시청각실)"
        },
        {
            "id": 45,
            "x": 1115,
            "y": 362,
            "name": "시청각실"
        },
        {
            "id": 46,
            "x": 1313,
            "y": 355,
            "name": "주차장"
        },
        {
            "id": 47,
            "x": 1219,
            "y": 300,
            "name": "1층 화장실 (급식실/남)"
        },
        {
            "id": 48,
            "x": 1244,
            "y": 301,
            "name": "1층 화장실 (급식실/여)"
        },
        {
            "id": 49,
            "x": 115,
            "y": 283,
            "name": "2층 복도 (Wee 클래스/계단)"
        },
        {
            "id": 50,
            "x": 141,
            "y": 283,
            "name": "2층 복도 (Wee 클래스/발간실)"
        },
        {
            "id": 51,
            "x": 185,
            "y": 283,
            "name": "2층 복도 (1-9)"
        },
        {
            "id": 52,
            "x": 226,
            "y": 283,
            "name": "2층 복도 (1-8)"
        },
        {
            "id": 53,
            "x": 269,
            "y": 282,
            "name": "2층 복도 (1-7)"
        },
        {
            "id": 54,
            "x": 321,
            "y": 284,
            "name": "2층 복도 (방송실)"
        },
        {
            "id": 55,
            "x": 394,
            "y": 288,
            "name": "2층 중앙 복도"
        },
        {
            "id": 56,
            "x": 459,
            "y": 284,
            "name": "2층 복도 (1-6)"
        },
        {
            "id": 57,
            "x": 507,
            "y": 283,
            "name": "2층 복도 (1-5)"
        },
        {
            "id": 58,
            "x": 552,
            "y": 283,
            "name": "2층 복도 (1-4)"
        },
        {
            "id": 59,
            "x": 594,
            "y": 283,
            "name": "2층 복도 (1-3)"
        },
        {
            "id": 60,
            "x": 633,
            "y": 281,
            "name": "2층 복도 (1-2)"
        },
        {
            "id": 61,
            "x": 677,
            "y": 283,
            "name": "2층 복도 (1-1)"
        },
        {
            "id": 62,
            "x": 706,
            "y": 283,
            "name": "1층 복도 (체육관)"
        },
        {
            "id": 63,
            "x": 553,
            "y": 389,
            "name": "2층 연결 통로"
        },
        {
            "id": 64,
            "x": 633,
            "y": 386,
            "name": "체육관"
        },
        {
            "id": 65,
            "x": 700,
            "y": 362,
            "name": "외부 계단"
        },
        {
            "id": 66,
            "x": 699,
            "y": 398,
            "name": "방송실/무대"
        },
        {
            "id": 67,
            "x": 560,
            "y": 356,
            "name": "2층 창고 (체육관)"
        },
        {
            "id": 68,
            "x": 546,
            "y": 369,
            "name": "2층 화장실 (체육관/여)"
        },
        {
            "id": 69,
            "x": 570,
            "y": 368,
            "name": "승강기 (외부/작동 X)"
        },
        {
            "id": 70,
            "x": 555,
            "y": 411,
            "name": "2층 화장실 (체육관/남)"
        },
        {
            "id": 71,
            "x": 1427,
            "y": 339,
            "name": "외부"
        },
        {
            "id": 72,
            "x": 359,
            "y": 353,
            "name": "2층 복도 (스페인어)"
        },
        {
            "id": 73,
            "x": 357,
            "y": 372,
            "name": "2층 복도 (스페인어)"
        },
        {
            "id": 74,
            "x": 359,
            "y": 391,
            "name": "2층 복도 (스페인어)"
        },
        {
            "id": 75,
            "x": 394,
            "y": 392,
            "name": "2층 복도 (스페인어/꿈소나무실)"
        },
        {
            "id": 76,
            "x": 435,
            "y": 418,
            "name": "2층 준비실 (꿈소나무실)"
        },
        {
            "id": 77,
            "x": 437,
            "y": 405,
            "name": "서버실"
        },
        {
            "id": 78,
            "x": 394,
            "y": 412,
            "name": "꿈소나무실"
        },
        {
            "id": 79,
            "x": 356,
            "y": 412,
            "name": "2층 휴계실 (꿈소나무실/여)"
        },
        {
            "id": 80,
            "x": 442,
            "y": 368,
            "name": "컴퓨터실"
        },
        {
            "id": 81,
            "x": 337,
            "y": 354,
            "name": "2층 화장실 (스페인어/남)"
        },
        {
            "id": 82,
            "x": 336,
            "y": 374,
            "name": "2층 화장실 (스페인어/여)"
        },
        {
            "id": 83,
            "x": 336,
            "y": 391,
            "name": "2층 계단 (스페인어)"
        },
        {
            "id": 84,
            "x": 319,
            "y": 304,
            "name": "2층 계단 (1-7)"
        },
        {
            "id": 85,
            "x": 283,
            "y": 314,
            "name": "2층 화장실 (1학년 뒷반/남)"
        },
        {
            "id": 86,
            "x": 262,
            "y": 314,
            "name": "2층 화장실 (1학년 뒷반/여)"
        },
        {
            "id": 87,
            "x": 238,
            "y": 314,
            "name": "진로 상담부"
        },
        {
            "id": 88,
            "x": 217,
            "y": 314,
            "name": "진로 상담실"
        },
        {
            "id": 89,
            "x": 186,
            "y": 314,
            "name": "시설 관리실"
        },
        {
            "id": 90,
            "x": 140,
            "y": 311,
            "name": "발간실"
        },
        {
            "id": 91,
            "x": 114,
            "y": 309,
            "name": "2층 계단 (Wee 클래스)"
        },
        {
            "id": 92,
            "x": 460,
            "y": 304,
            "name": "2층 복도 (1-6)"
        },
        {
            "id": 93,
            "x": 495,
            "y": 309,
            "name": "2층 화장실 (1학년 앞반/남)"
        },
        {
            "id": 94,
            "x": 519,
            "y": 310,
            "name": "2층 화장실 (1학년 앞반/여)"
        },
        {
            "id": 95,
            "x": 548,
            "y": 314,
            "name": "1학년부"
        },
        {
            "id": 96,
            "x": 575,
            "y": 313,
            "name": "비품실"
        },
        {
            "id": 97,
            "x": 598,
            "y": 314,
            "name": "학생 인권 안전부"
        },
        {
            "id": 98,
            "x": 635,
            "y": 310,
            "name": "스마트 1실 (학생회의실)"
        },
        {
            "id": 99,
            "x": 676,
            "y": 316,
            "name": "청소물품 보관실"
        },
        {
            "id": 100,
            "x": 707,
            "y": 258,
            "name": "2층 계단 (1-1)"
        },
        {
            "id": 101,
            "x": 676,
            "y": 257,
            "name": "1-1"
        },
        {
            "id": 102,
            "x": 632,
            "y": 258,
            "name": "1-2"
        },
        {
            "id": 103,
            "x": 593,
            "y": 259,
            "name": "1-3"
        },
        {
            "id": 104,
            "x": 552,
            "y": 258,
            "name": "1-4"
        },
        {
            "id": 105,
            "x": 506,
            "y": 258,
            "name": "1-5"
        },
        {
            "id": 106,
            "x": 458,
            "y": 258,
            "name": "1-6"
        },
        {
            "id": 107,
            "x": 390,
            "y": 279,
            "name": "칸막이 탈의실"
        },
        {
            "id": 108,
            "x": 392,
            "y": 258,
            "name": "고사본부"
        },
        {
            "id": 109,
            "x": 333,
            "y": 258,
            "name": "교육 정보부"
        },
        {
            "id": 110,
            "x": 308,
            "y": 258,
            "name": "방송실"
        },
        {
            "id": 111,
            "x": 274,
            "y": 258,
            "name": "1-7"
        },
        {
            "id": 112,
            "x": 227,
            "y": 259,
            "name": "1-8"
        },
        {
            "id": 113,
            "x": 186,
            "y": 259,
            "name": "1-9"
        },
        {
            "id": 114,
            "x": 142,
            "y": 259,
            "name": "Wee 클래스"
        },
        {
            "id": 115,
            "x": 394,
            "y": 363,
            "name": "솔향기실(스페인어)"
        },
        {
            "id": 116,
            "x": 396,
            "y": 338,
            "name": "2층 다리 뒤 복도"
        },
        {
            "id": 117,
            "x": 1584,
            "y": 100,
            "name": "3층 복도 (2-9)"
        },
        {
            "id": 118,
            "x": 1635,
            "y": 101,
            "name": "3층 복도 (2-8)"
        },
        {
            "id": 119,
            "x": 1676,
            "y": 101,
            "name": "3층 복도 (2-7)"
        },
        {
            "id": 120,
            "x": 1720,
            "y": 100,
            "name": "3층 복도 (2-6)"
        },
        {
            "id": 121,
            "x": 1761,
            "y": 101,
            "name": "3층 복도 (계단)"
        },
        {
            "id": 122,
            "x": 1833,
            "y": 116,
            "name": "3층 중앙 복도"
        },
        {
            "id": 123,
            "x": 1905,
            "y": 100,
            "name": "3층 복도 (2-5)"
        },
        {
            "id": 124,
            "x": 1955,
            "y": 101,
            "name": "3층 복도 (2-4)"
        },
        {
            "id": 125,
            "x": 1999,
            "y": 101,
            "name": "3층 복도 (2-3)"
        },
        {
            "id": 126,
            "x": 2040,
            "y": 101,
            "name": "3층 복도 (2-2)"
        },
        {
            "id": 127,
            "x": 2083,
            "y": 100,
            "name": "3층 복도 (2-1)"
        },
        {
            "id": 128,
            "x": 2125,
            "y": 100,
            "name": "3층 복도 (이동수업실/동아리실(댄스))"
        },
        {
            "id": 129,
            "x": 1791,
            "y": 143,
            "name": "3층 다리 복도 (2학년 뒷반 쪽)"
        },
        {
            "id": 130,
            "x": 1886,
            "y": 144,
            "name": "3층 다리 복도 (2학년 앞반 쪽)"
        },
        {
            "id": 131,
            "x": 1806,
            "y": 168,
            "name": "3층 복도 (음악실)"
        },
        {
            "id": 132,
            "x": 1808,
            "y": 189,
            "name": "3층 복도 (음악실)"
        },
        {
            "id": 133,
            "x": 1808,
            "y": 205,
            "name": "3층 복도 (음악실)"
        },
        {
            "id": 134,
            "x": 1835,
            "y": 154,
            "name": "3층 복도 (음악실)"
        },
        {
            "id": 135,
            "x": 1787,
            "y": 168,
            "name": "3층 화장실 (음악실/남)"
        },
        {
            "id": 136,
            "x": 1788,
            "y": 187,
            "name": "3층 화장실 (음악실/여)"
        },
        {
            "id": 137,
            "x": 1785,
            "y": 205,
            "name": "3층 계단 (음악실)"
        },
        {
            "id": 138,
            "x": 1831,
            "y": 185,
            "name": "음악실"
        },
        {
            "id": 139,
            "x": 1861,
            "y": 172,
            "name": "3층 준비실 (미술실)"
        },
        {
            "id": 140,
            "x": 1863,
            "y": 199,
            "name": "3층 준비실 (미술실)"
        },
        {
            "id": 141,
            "x": 1888,
            "y": 184,
            "name": "미술실"
        },
        {
            "id": 142,
            "x": 2156,
            "y": 81,
            "name": "3층 계단 (이동수업실)"
        },
        {
            "id": 143,
            "x": 2129,
            "y": 80,
            "name": "3층 이동수업실"
        },
        {
            "id": 144,
            "x": 2080,
            "y": 82,
            "name": "2-1"
        },
        {
            "id": 145,
            "x": 2041,
            "y": 81,
            "name": "2-2"
        },
        {
            "id": 146,
            "x": 2000,
            "y": 81,
            "name": "2-3"
        },
        {
            "id": 147,
            "x": 1954,
            "y": 82,
            "name": "2-4"
        },
        {
            "id": 148,
            "x": 1906,
            "y": 82,
            "name": "2-5"
        },
        {
            "id": 149,
            "x": 1817,
            "y": 89,
            "name": "본교무실/2학년부"
        },
        {
            "id": 150,
            "x": 1719,
            "y": 82,
            "name": "2-6"
        },
        {
            "id": 151,
            "x": 1683,
            "y": 82,
            "name": "2-7"
        },
        {
            "id": 152,
            "x": 1639,
            "y": 83,
            "name": "2-8"
        },
        {
            "id": 153,
            "x": 1595,
            "y": 83,
            "name": "2-9"
        },
        {
            "id": 154,
            "x": 1560,
            "y": 120,
            "name": "2층 계단 (2-9)"
        },
        {
            "id": 155,
            "x": 1580,
            "y": 119,
            "name": "창의 인문 인재부"
        },
        {
            "id": 156,
            "x": 1602,
            "y": 121,
            "name": "스마트 3실"
        },
        {
            "id": 157,
            "x": 1654,
            "y": 135,
            "name": "3층 홈베이스-2"
        },
        {
            "id": 158,
            "x": 1709,
            "y": 140,
            "name": "3층 화장실 (2학년 뒷반/여)"
        },
        {
            "id": 159,
            "x": 1736,
            "y": 141,
            "name": "3층 화장실 (2학년 뒷반/남)"
        },
        {
            "id": 160,
            "x": 1765,
            "y": 130,
            "name": "3층 계단 (2-6)"
        },
        {
            "id": 161,
            "x": 1911,
            "y": 129,
            "name": "3층 계단 (2-5)"
        },
        {
            "id": 162,
            "x": 1946,
            "y": 131,
            "name": "3층 화장실 (2학년 앞반/남)"
        },
        {
            "id": 163,
            "x": 1970,
            "y": 132,
            "name": "3층 화장실 (2학년 앞반/여)"
        },
        {
            "id": 164,
            "x": 2000,
            "y": 141,
            "name": "3층 홈베이스-1"
        },
        {
            "id": 165,
            "x": 2045,
            "y": 127,
            "name": "성희롱 고충 상담실"
        },
        {
            "id": 166,
            "x": 2085,
            "y": 133,
            "name": "스마트 2실"
        },
        {
            "id": 167,
            "x": 2127,
            "y": 134,
            "name": "동아리실(댄스)"
        },
        {
            "id": 168,
            "x": 855,
            "y": 101,
            "name": "4층 복도 (3-9)"
        },
        {
            "id": 169,
            "x": 906,
            "y": 102,
            "name": "4층 복도 (3-8)"
        },
        {
            "id": 170,
            "x": 950,
            "y": 101,
            "name": "4층 복도 (3-7)"
        },
        {
            "id": 171,
            "x": 995,
            "y": 100,
            "name": "4층 복도 (3-6)"
        },
        {
            "id": 172,
            "x": 1043,
            "y": 101,
            "name": "4층 복도 (송죽실)"
        },
        {
            "id": 173,
            "x": 1114,
            "y": 101,
            "name": "4층 복도 (3학년부)"
        },
        {
            "id": 174,
            "x": 1067,
            "y": 125,
            "name": "4층 다리 복도 (물리/지구 과학실)"
        },
        {
            "id": 175,
            "x": 1160,
            "y": 127,
            "name": "4층 다리 복도 (융합과학부)"
        },
        {
            "id": 176,
            "x": 1182,
            "y": 102,
            "name": "4층 복도 (3-5)"
        },
        {
            "id": 177,
            "x": 1225,
            "y": 101,
            "name": "4층 복도 (3-4)"
        },
        {
            "id": 178,
            "x": 1276,
            "y": 101,
            "name": "4층 복도 (3-3)"
        },
        {
            "id": 179,
            "x": 1320,
            "y": 101,
            "name": "4층 복도 (3-2)"
        },
        {
            "id": 180,
            "x": 1363,
            "y": 101,
            "name": "4층 복도 (3-1)"
        },
        {
            "id": 181,
            "x": 1400,
            "y": 101,
            "name": "4층 복도 (이동수업실)"
        },
        {
            "id": 182,
            "x": 1114,
            "y": 151,
            "name": "4층 복도 (융합과학실)"
        },
        {
            "id": 183,
            "x": 1083,
            "y": 165,
            "name": "4층 복도 (융합과학실)"
        },
        {
            "id": 184,
            "x": 1082,
            "y": 180,
            "name": "4층 복도 (융합과학실)"
        },
        {
            "id": 185,
            "x": 1083,
            "y": 201,
            "name": "4층 복도 (융합과학실)"
        },
        {
            "id": 186,
            "x": 1137,
            "y": 196,
            "name": "4층 준비실 (화학/생명 과학실)"
        },
        {
            "id": 187,
            "x": 1136,
            "y": 169,
            "name": "4층 준비실 (융합 과학실)"
        },
        {
            "id": 188,
            "x": 1110,
            "y": 185,
            "name": "융합 과학실"
        },
        {
            "id": 189,
            "x": 1163,
            "y": 183,
            "name": "화학/생명 과학실"
        },
        {
            "id": 190,
            "x": 1062,
            "y": 166,
            "name": "4층 화장실 (융합과학실/남)"
        },
        {
            "id": 191,
            "x": 1063,
            "y": 186,
            "name": "4층 화장실 (융합과학실/여)"
        },
        {
            "id": 192,
            "x": 1063,
            "y": 203,
            "name": "4층 계단 (융합과학실)"
        },
        {
            "id": 193,
            "x": 840,
            "y": 121,
            "name": "4층 계단 (2-9)"
        },
        {
            "id": 194,
            "x": 857,
            "y": 123,
            "name": "플로터실"
        },
        {
            "id": 195,
            "x": 876,
            "y": 126,
            "name": "스마트 6실"
        },
        {
            "id": 196,
            "x": 932,
            "y": 136,
            "name": "4층 홈베이스-2"
        },
        {
            "id": 197,
            "x": 986,
            "y": 138,
            "name": "4층 화장실 (3학년 뒷반/여)"
        },
        {
            "id": 198,
            "x": 1009,
            "y": 140,
            "name": "4층 화장실 (3학년 뒷반/남)"
        },
        {
            "id": 199,
            "x": 1042,
            "y": 129,
            "name": "4층 계단 (3-6)"
        },
        {
            "id": 200,
            "x": 1100,
            "y": 130,
            "name": "물리/지구 과학실"
        },
        {
            "id": 201,
            "x": 1141,
            "y": 130,
            "name": "융합과학부"
        },
        {
            "id": 202,
            "x": 1222,
            "y": 133,
            "name": "4층 화장실 (3학년 앞반/남)"
        },
        {
            "id": 203,
            "x": 1244,
            "y": 134,
            "name": "4층 화장실 (3학년 앞반/여)"
        },
        {
            "id": 204,
            "x": 1276,
            "y": 138,
            "name": "4층 홈베이스-1"
        },
        {
            "id": 205,
            "x": 1306,
            "y": 136,
            "name": "4층 서고"
        },
        {
            "id": 206,
            "x": 1358,
            "y": 124,
            "name": "스마트 5실"
        },
        {
            "id": 207,
            "x": 1400,
            "y": 123,
            "name": "스마트 4실"
        },
        {
            "id": 208,
            "x": 1430,
            "y": 81,
            "name": "4층 계단 (이동수업실)"
        },
        {
            "id": 209,
            "x": 1407,
            "y": 82,
            "name": "4층 이동수업실"
        },
        {
            "id": 210,
            "x": 1356,
            "y": 81,
            "name": "3-1"
        },
        {
            "id": 211,
            "x": 1313,
            "y": 81,
            "name": "3-2"
        },
        {
            "id": 212,
            "x": 1275,
            "y": 82,
            "name": "3-3"
        },
        {
            "id": 213,
            "x": 1236,
            "y": 83,
            "name": "3-4"
        },
        {
            "id": 214,
            "x": 1182,
            "y": 83,
            "name": "3-5"
        },
        {
            "id": 215,
            "x": 1118,
            "y": 84,
            "name": "3학년부"
        },
        {
            "id": 216,
            "x": 1045,
            "y": 82,
            "name": "송죽실"
        },
        {
            "id": 217,
            "x": 991,
            "y": 82,
            "name": "3-6"
        },
        {
            "id": 218,
            "x": 949,
            "y": 84,
            "name": "3-7"
        },
        {
            "id": 219,
            "x": 907,
            "y": 84,
            "name": "3-8"
        },
        {
            "id": 220,
            "x": 869,
            "y": 82,
            "name": "3-9"
        },
        {
            "id": 221,
            "x": 1186,
            "y": 129,
            "name": "4층 계단 (3-5)"
        },
        {
            "id": 222,
            "x": 1326,
            "y": 127,
            "name": "관리자 연구실/학폭 상담실"
        },
        {
            "id": 223,
            "x": 364,
            "y": 94,
            "name": "도서관"
        },
        {
            "id": 224,
            "x": 409,
            "y": 95,
            "name": "자습실"
        },
        {
            "id": 225,
            "x": 332,
            "y": 88,
            "name": "서고"
        },
        {
            "id": 226,
            "x": 443,
            "y": 87,
            "name": "서고"
        },
        {
            "id": 227,
            "x": 334,
            "y": 103,
            "name": "5층 계단 (도서관)"
        },
        {
            "id": 228,
            "x": 444,
            "y": 103,
            "name": "5층 계단 (자습실)"
        }
    ],
    "edges": [
        [
            0,
            1
        ],
        [
            1,
            2
        ],
        [
            2,
            3
        ],
        [
            3,
            4
        ],
        [
            4,
            5
        ],
        [
            5,
            6
        ],
        [
            6,
            7
        ],
        [
            7,
            8
        ],
        [
            6,
            9
        ],
        [
            0,
            12
        ],
        [
            0,
            11
        ],
        [
            2,
            15
        ],
        [
            1,
            25
        ],
        [
            15,
            13
        ],
        [
            15,
            14
        ],
        [
            2,
            24
        ],
        [
            24,
            26
        ],
        [
            3,
            23
        ],
        [
            3,
            22
        ],
        [
            4,
            21
        ],
        [
            4,
            20
        ],
        [
            3,
            16
        ],
        [
            4,
            17
        ],
        [
            5,
            18
        ],
        [
            5,
            19
        ],
        [
            9,
            40
        ],
        [
            9,
            45
        ],
        [
            9,
            10
        ],
        [
            10,
            41
        ],
        [
            10,
            42
        ],
        [
            10,
            43
        ],
        [
            45,
            44
        ],
        [
            7,
            28
        ],
        [
            7,
            29
        ],
        [
            7,
            27
        ],
        [
            8,
            30
        ],
        [
            8,
            47
        ],
        [
            8,
            48
        ],
        [
            8,
            32
        ],
        [
            32,
            31
        ],
        [
            31,
            33
        ],
        [
            34,
            33
        ],
        [
            33,
            35
        ],
        [
            34,
            36
        ],
        [
            34,
            37
        ],
        [
            32,
            38
        ],
        [
            32,
            39
        ],
        [
            6,
            46
        ],
        [
            38,
            46
        ],
        [
            71,
            65
        ],
        [
            49,
            50
        ],
        [
            50,
            51
        ],
        [
            51,
            52
        ],
        [
            53,
            52
        ],
        [
            53,
            54
        ],
        [
            54,
            55
        ],
        [
            55,
            56
        ],
        [
            56,
            57
        ],
        [
            57,
            58
        ],
        [
            58,
            59
        ],
        [
            59,
            60
        ],
        [
            60,
            61
        ],
        [
            61,
            62
        ],
        [
            62,
            63
        ],
        [
            49,
            91
        ],
        [
            50,
            90
        ],
        [
            50,
            114
        ],
        [
            51,
            113
        ],
        [
            52,
            112
        ],
        [
            53,
            111
        ],
        [
            54,
            110
        ],
        [
            54,
            109
        ],
        [
            55,
            107
        ],
        [
            55,
            108
        ],
        [
            56,
            106
        ],
        [
            57,
            105
        ],
        [
            58,
            104
        ],
        [
            59,
            103
        ],
        [
            60,
            102
        ],
        [
            61,
            101
        ],
        [
            61,
            100
        ],
        [
            51,
            89
        ],
        [
            52,
            87
        ],
        [
            87,
            88
        ],
        [
            53,
            86
        ],
        [
            53,
            85
        ],
        [
            54,
            84
        ],
        [
            56,
            92
        ],
        [
            57,
            93
        ],
        [
            57,
            94
        ],
        [
            58,
            95
        ],
        [
            95,
            96
        ],
        [
            59,
            97
        ],
        [
            60,
            98
        ],
        [
            61,
            99
        ],
        [
            63,
            68
        ],
        [
            63,
            69
        ],
        [
            63,
            67
        ],
        [
            63,
            70
        ],
        [
            63,
            64
        ],
        [
            64,
            66
        ],
        [
            55,
            116
        ],
        [
            116,
            72
        ],
        [
            72,
            81
        ],
        [
            72,
            73
        ],
        [
            82,
            73
        ],
        [
            73,
            74
        ],
        [
            74,
            83
        ],
        [
            74,
            79
        ],
        [
            74,
            75
        ],
        [
            75,
            80
        ],
        [
            75,
            78
        ],
        [
            78,
            76
        ],
        [
            80,
            77
        ],
        [
            116,
            115
        ],
        [
            11,
            91
        ],
        [
            19,
            84
        ],
        [
            92,
            28
        ],
        [
            38,
            100
        ],
        [
            42,
            83
        ],
        [
            141,
            139
        ],
        [
            141,
            140
        ],
        [
            138,
            134
        ],
        [
            141,
            130
        ],
        [
            134,
            129
        ],
        [
            134,
            130
        ],
        [
            129,
            122
        ],
        [
            130,
            122
        ],
        [
            131,
            135
        ],
        [
            132,
            136
        ],
        [
            133,
            137
        ],
        [
            133,
            132
        ],
        [
            131,
            132
        ],
        [
            131,
            129
        ],
        [
            131,
            134
        ],
        [
            117,
            118
        ],
        [
            118,
            119
        ],
        [
            119,
            120
        ],
        [
            120,
            121
        ],
        [
            121,
            122
        ],
        [
            122,
            123
        ],
        [
            123,
            124
        ],
        [
            124,
            125
        ],
        [
            125,
            126
        ],
        [
            126,
            127
        ],
        [
            127,
            128
        ],
        [
            117,
            154
        ],
        [
            117,
            155
        ],
        [
            117,
            156
        ],
        [
            118,
            157
        ],
        [
            117,
            153
        ],
        [
            119,
            157
        ],
        [
            118,
            152
        ],
        [
            119,
            151
        ],
        [
            120,
            150
        ],
        [
            120,
            158
        ],
        [
            120,
            159
        ],
        [
            121,
            160
        ],
        [
            122,
            149
        ],
        [
            123,
            148
        ],
        [
            124,
            147
        ],
        [
            125,
            146
        ],
        [
            126,
            145
        ],
        [
            127,
            144
        ],
        [
            128,
            143
        ],
        [
            128,
            142
        ],
        [
            128,
            167
        ],
        [
            127,
            166
        ],
        [
            126,
            165
        ],
        [
            125,
            164
        ],
        [
            124,
            163
        ],
        [
            124,
            162
        ],
        [
            123,
            161
        ],
        [
            154,
            91
        ],
        [
            160,
            84
        ],
        [
            161,
            92
        ],
        [
            142,
            100
        ],
        [
            137,
            83
        ],
        [
            174,
            182
        ],
        [
            175,
            182
        ],
        [
            189,
            186
        ],
        [
            188,
            187
        ],
        [
            182,
            188
        ],
        [
            175,
            189
        ],
        [
            174,
            183
        ],
        [
            182,
            183
        ],
        [
            183,
            190
        ],
        [
            184,
            191
        ],
        [
            185,
            192
        ],
        [
            183,
            184
        ],
        [
            184,
            185
        ],
        [
            168,
            169
        ],
        [
            169,
            170
        ],
        [
            170,
            171
        ],
        [
            171,
            172
        ],
        [
            172,
            173
        ],
        [
            173,
            176
        ],
        [
            177,
            176
        ],
        [
            177,
            178
        ],
        [
            178,
            179
        ],
        [
            179,
            180
        ],
        [
            180,
            181
        ],
        [
            181,
            208
        ],
        [
            181,
            209
        ],
        [
            180,
            210
        ],
        [
            179,
            211
        ],
        [
            178,
            212
        ],
        [
            177,
            213
        ],
        [
            176,
            214
        ],
        [
            173,
            215
        ],
        [
            172,
            216
        ],
        [
            171,
            217
        ],
        [
            170,
            218
        ],
        [
            169,
            219
        ],
        [
            168,
            220
        ],
        [
            168,
            193
        ],
        [
            168,
            194
        ],
        [
            168,
            195
        ],
        [
            169,
            196
        ],
        [
            170,
            196
        ],
        [
            171,
            197
        ],
        [
            171,
            198
        ],
        [
            172,
            199
        ],
        [
            173,
            174
        ],
        [
            176,
            221
        ],
        [
            177,
            202
        ],
        [
            177,
            203
        ],
        [
            178,
            204
        ],
        [
            179,
            222
        ],
        [
            222,
            205
        ],
        [
            180,
            206
        ],
        [
            181,
            207
        ],
        [
            173,
            200
        ],
        [
            173,
            201
        ],
        [
            173,
            175
        ],
        [
            208,
            142
        ],
        [
            192,
            137
        ],
        [
            193,
            154
        ],
        [
            199,
            160
        ],
        [
            221,
            161
        ],
        [
            224,
            226
        ],
        [
            223,
            225
        ],
        [
            223,
            224
        ],
        [
            224,
            228
        ],
        [
            223,
            227
        ],
        [
            228,
            221
        ],
        [
            227,
            199
        ],
        [
            71,
            46
        ]
    ]
}